pycritic/__init__.py
pycritic/base/__init__.py
pycritic/base/checker.py
pycritic/base/criterion.py
pycritic/json/__init__.py
pycritic/json/checker_builder.py
pycritic/json/criterion_builder.py
pycritic/json/suite_builder.py
pycritic/remote/__init__.py
pycritic/remote/remote_criterion.py
pycritic-0.2.3.dist-info/METADATA
pycritic-0.2.3.dist-info/WHEEL
pycritic-0.2.3.dist-info/top_level.txt
pycritic-0.2.3.dist-info/RECORD
