Metadata-Version: 2.1
Name: pycritic
Version: 0.2.3
Summary: A package for estimating a set of parameters
Home-page: https://github.com/Alexcoratt/pycritic
Author: Alexander Smirnov
Author-email: aleqsonder@icloud.com
Classifier: Programming Language :: Python :: 3
Classifier: Operating System :: OS Independent
Requires-Python: >=3.11
Requires-Dist: jsonschema
Requires-Dist: requests
